ds/__init__.py
ds/__main__.py
ds/args.py
ds/configs.py
ds/env.py
ds/runner.py
ds/searchers.py
ds/symbols.py
ds/tasks.py
ds/parsers/__init__.py
ds/parsers/cargo_toml.py
ds/parsers/composer_json.py
ds/parsers/ds_toml.py
ds/parsers/makefile.py
ds/parsers/package_json.py
ds/parsers/pyproject_pdm.py
ds/parsers/pyproject_poetry.py
ds/parsers/pyproject_rye.py
ds/parsers/pyproject_toml.py
ds/parsers/toml.py
ds/parsers/uv_toml.py
ds_run-1.3.0.dist-info/LICENSE.md
ds_run-1.3.0.dist-info/METADATA
ds_run-1.3.0.dist-info/WHEEL
ds_run-1.3.0.dist-info/entry_points.txt
ds_run-1.3.0.dist-info/top_level.txt
ds_run-1.3.0.dist-info/RECORD
