Metadata-Version: 2.1
Name: ds-run
Version: 1.3.0
Summary: run dev scripts
Author-email: Metaist LLC <metaist@metaist.com>
License: MIT
Project-URL: Homepage, https://github.com/metaist/ds
Project-URL: Documentation, https://metaist.github.io/ds/
Project-URL: Repository, https://github.com/metaist/ds.git
Project-URL: Changelog, https://github.com/metaist/ds/blob/main/CHANGELOG.md
Keywords: dev,scripts
Classifier: Development Status :: 4 - Beta
Classifier: Intended Audience :: Developers
Classifier: License :: OSI Approved :: MIT License
Classifier: Natural Language :: English
Classifier: Operating System :: OS Independent
Classifier: Programming Language :: Python
Classifier: Programming Language :: Python :: 3
Classifier: Programming Language :: Python :: 3 :: Only
Classifier: Programming Language :: Python :: 3.8
Classifier: Programming Language :: Python :: 3.9
Classifier: Programming Language :: Python :: 3.10
Classifier: Programming Language :: Python :: 3.11
Classifier: Programming Language :: Python :: 3.12
Classifier: Topic :: Software Development :: Build Tools
Classifier: Typing :: Typed
Requires-Python: >=3.8
License-File: LICENSE.md
Requires-Dist: tomli==2.0.1; python_version < "3.11"
Requires-Dist: graphlib-backport==1.1.0; python_version < "3.9"
Provides-Extra: dev
Requires-Dist: build; extra == "dev"
Requires-Dist: cogapp; extra == "dev"
Requires-Dist: coverage; extra == "dev"
Requires-Dist: mypy; extra == "dev"
Requires-Dist: pdoc3; extra == "dev"
Requires-Dist: pip; extra == "dev"
Requires-Dist: pyright; extra == "dev"
Requires-Dist: pytest-cov; extra == "dev"
Requires-Dist: pytest; extra == "dev"
Requires-Dist: ruff; extra == "dev"
